COPYRIGHT
LICENSE
MANIFEST.in
README
setup.cfg
setup.py
tryton.cfg
webdav.xml
./__init__.py
./protocol.py
./server.py
./tryton.cfg
./webdav.py
./webdav.xml
./locale/bg.po
./locale/ca.po
./locale/cs.po
./locale/de.po
./locale/es.po
./locale/fr.po
./locale/hu_HU.po
./locale/it_IT.po
./locale/ja_JP.po
./locale/lo.po
./locale/lt.po
./locale/nl.po
./locale/pl.po
./locale/pt_BR.po
./locale/ru.po
./locale/sl.po
./locale/zh_CN.po
./tests/__init__.py
./tests/test_webdav.py
./view/attachment_form.xml
./view/collection_form.xml
./view/collection_list.xml
./view/collection_tree.xml
./view/share_form.xml
./view/share_list.xml
bin/trytond-webdav
doc/index.rst
locale/bg.po
locale/ca.po
locale/cs.po
locale/de.po
locale/es.po
locale/fr.po
locale/hu_HU.po
locale/it_IT.po
locale/ja_JP.po
locale/lo.po
locale/lt.po
locale/nl.po
locale/pl.po
locale/pt_BR.po
locale/ru.po
locale/sl.po
locale/zh_CN.po
trytond_webdav3.egg-info/PKG-INFO
trytond_webdav3.egg-info/SOURCES.txt
trytond_webdav3.egg-info/dependency_links.txt
trytond_webdav3.egg-info/entry_points.txt
trytond_webdav3.egg-info/not-zip-safe
trytond_webdav3.egg-info/requires.txt
trytond_webdav3.egg-info/top_level.txt
view/attachment_form.xml
view/collection_form.xml
view/collection_list.xml
view/collection_tree.xml
view/share_form.xml
view/share_list.xml