Metadata-Version: 1.1
Name: trytond-webdav3
Version: 4.2.2
Summary: GNU Health WebDAV server for Python 3
Home-page: http://health.gnu.org
Author: GNU Solidario
Author-email: health@gnusolidario.org
License: GPL-3
Download-URL: http://ftp.gnu.org/gnu/health/
Keywords: webdav GNUHealth
Platform: UNKNOWN
Classifier: Development Status :: 5 - Production/Stable
Classifier: Environment :: Plugins
Classifier: Framework :: Tryton
Classifier: Intended Audience :: Developers
Classifier: Intended Audience :: Financial and Insurance Industry
Classifier: Intended Audience :: Legal Industry
Classifier: Intended Audience :: Manufacturing
Classifier: License :: OSI Approved :: GNU General Public License (GPL)
Classifier: Natural Language :: Bulgarian
Classifier: Natural Language :: Catalan
Classifier: Natural Language :: Chinese (Simplified)
Classifier: Natural Language :: Czech
Classifier: Natural Language :: Dutch
Classifier: Natural Language :: English
Classifier: Natural Language :: French
Classifier: Natural Language :: German
Classifier: Natural Language :: Hungarian
Classifier: Natural Language :: Italian
Classifier: Natural Language :: Polish
Classifier: Natural Language :: Portuguese (Brazilian)
Classifier: Natural Language :: Russian
Classifier: Natural Language :: Slovenian
Classifier: Natural Language :: Spanish
Classifier: Operating System :: OS Independent
Classifier: Programming Language :: Python :: 3
Classifier: Topic :: Office/Business
